patch_env.pth
patch_env/__init__.py
patch_env-1.0.0.dist-info/LICENSE
patch_env-1.0.0.dist-info/METADATA
patch_env-1.0.0.dist-info/WHEEL
patch_env-1.0.0.dist-info/top_level.txt
patch_env-1.0.0.dist-info/RECORD
