Metadata-Version: 2.1
Name: patch-env
Version: 1.0.0
Summary: Patch os.environ with dynamic values when the interpreter starts
Home-page: https://github.com/caricalabs/patch-env
Author: Carica Labs, LLC
Author-email: info@caricalabs.com
License: APL 2.0
Keywords: patch environment dynamic hook os.environ
Platform: UNKNOWN
Classifier: Development Status :: 5 - Production/Stable
Classifier: Intended Audience :: Developers
Classifier: License :: OSI Approved :: Apache Software License
Classifier: Programming Language :: Python :: 3.7
Provides-Extra: dev
Requires-Dist: check-manifest ; extra == 'dev'
Provides-Extra: test
